package/Analyzer.py
package/__init__.py
package/cat.py
package/config.py
package/es.py
package/indices.py
package/main.py
elasticsearch_lite_wrapper-1.0.0.dist-info/LICENSE
elasticsearch_lite_wrapper-1.0.0.dist-info/METADATA
elasticsearch_lite_wrapper-1.0.0.dist-info/WHEEL
elasticsearch_lite_wrapper-1.0.0.dist-info/top_level.txt
elasticsearch_lite_wrapper-1.0.0.dist-info/RECORD
