Metadata-Version: 2.1
Name: elasticsearch-lite-wrapper
Version: 1.0.0
Summary: A lightsweight elasticsearch client
Home-page: https://github.com/sanchitd9/es-client
Author: Sanchit Dass
Author-email: sanchitd9@gmail.com
License: UNKNOWN
Platform: UNKNOWN
Classifier: Programming Language :: Python :: 3
Classifier: License :: OSI Approved :: MIT License
Classifier: Operating System :: OS Independent
Requires-Python: >=3.1.2
